{
  "project_info": {
    "project_number": "787614864142",
    "project_id": "forte-mobile-c7997",
    "storage_bucket": "forte-mobile-c7997.appspot.com"
  },
  "client": [
    {
      "client_info": {
        "mobilesdk_app_id": "1:787614864142:android:cefae16a305d8aa5367d5f",
        "android_client_info": {
          "package_name": "ua.com.forte_life"
        }
      },
      "oauth_client": [
        {
          "client_id": "787614864142-ikjahpm3q4le7ds467esf48p2278gn5t.apps.googleusercontent.com",
          "client_type": 3
        }
      ],
      "api_key": [
        {
          "current_key": "AIzaSyDQ6guVrwPHi8JNf9xkchCypdTaToyWbs0"
        }
      ],
      "services": {
        "appinvite_service": {
          "other_platform_oauth_client": [
            {
              "client_id": "787614864142-ikjahpm3q4le7ds467esf48p2278gn5t.apps.googleusercontent.com",
              "client_type": 3
            }
          ]
        }
      }
    }
  ],
  "configuration_version": "1"
}